{
  "items" : [
    {
      "data" : {
        "tag" : "UI.Track.UrlD",
        "contents" : {
          "url" : "http:\/\/allaboutexplorers.com\/"
        }
      },
      "title" : "allaboutexplorers.com",
      "view" : {
        "tag" : "UI.ContentViews.Views.WebView"
      },
      "subtitle" : "allaboutexplorers.com",
      "expanded" : true,
      "children" : [

      ]
    },
    {
      "data" : {
        "tag" : "UI.Track.UrlD",
        "contents" : {
          "url" : "http:\/\/www.digitalhistory.uh.edu\/"
        }
      },
      "title" : "www.digitalhistory.uh.edu",
      "view" : {
        "tag" : "UI.ContentViews.Views.WebView"
      },
      "subtitle" : "www.digitalhistory.uh.edu",
      "expanded" : true,
      "children" : [

      ]
    },
    {
      "data" : {
        "tag" : "UI.Track.UrlD",
        "contents" : {
          "url" : "http:\/\/www.havefunwithhistory.com\/"
        }
      },
      "title" : "www.havefunwithhistory.com",
      "view" : {
        "tag" : "UI.ContentViews.Views.WebView"
      },
      "subtitle" : "www.havefunwithhistory.com",
      "expanded" : true,
      "children" : [

      ]
    },
    {
      "data" : {
        "tag" : "UI.Track.UrlD",
        "contents" : {
          "url" : "http:\/\/www.history.com\/topics"
        }
      },
      "title" : "www.history.com",
      "view" : {
        "tag" : "UI.ContentViews.Views.WebView"
      },
      "subtitle" : "www.history.com",
      "expanded" : true,
      "children" : [

      ]
    },
    {
      "data" : {
        "tag" : "UI.Track.UrlD",
        "contents" : {
          "url" : "http:\/\/www.history-timelines.org.uk\/"
        }
      },
      "title" : "www.history-timelines.org.uk",
      "view" : {
        "tag" : "UI.ContentViews.Views.WebView"
      },
      "subtitle" : "www.history-timelines.org.uk",
      "expanded" : true,
      "children" : [

      ]
    },
    {
      "data" : {
        "tag" : "UI.Track.UrlD",
        "contents" : {
          "url" : "http:\/\/www.hyperhistory.com\/online_n2\/History_n2\/a.html"
        }
      },
      "title" : "www.hyperhistory.com",
      "view" : {
        "tag" : "UI.ContentViews.Views.WebView"
      },
      "subtitle" : "www.hyperhistory.com",
      "expanded" : true,
      "children" : [

      ]
    },
    {
      "data" : {
        "tag" : "UI.Track.UrlD",
        "contents" : {
          "url" : "http:\/\/en.wikipedia.org\/wiki\/List_of_Presidents_of_the_United_States"
        }
      },
      "title" : "List Of US Presidents",
      "view" : {
        "tag" : "UI.ContentViews.Views.WebView"
      },
      "subtitle" : "en.wikipedia.org",
      "expanded" : true,
      "children" : [

      ]
    },
    {
      "data" : {
        "tag" : "UI.Track.UrlD",
        "contents" : {
          "url" : "http:\/\/memorize.com\/us-presidents"
        }
      },
      "title" : "Memorize US Presidents",
      "view" : {
        "tag" : "UI.ContentViews.Views.WebView"
      },
      "subtitle" : "memorize.com",
      "expanded" : true,
      "children" : [

      ]
    },
    {
      "data" : {
        "tag" : "UI.Track.UrlD",
        "contents" : {
          "url" : "http:\/\/en.wikipedia.org\/wiki\/List_of_time_periods"
        }
      },
      "title" : "List Of Time Periods",
      "view" : {
        "tag" : "UI.ContentViews.Views.WebView"
      },
      "subtitle" : "en.wikipedia.org",
      "expanded" : true,
      "children" : [

      ]
    },
    {
      "data" : {
        "tag" : "UI.Track.UrlD",
        "contents" : {
          "url" : "http:\/\/www.fsmitha.com\/"
        }
      },
      "title" : "Macro History",
      "view" : {
        "tag" : "UI.ContentViews.Views.WebView"
      },
      "subtitle" : "www.fsmitha.com",
      "expanded" : true,
      "children" : [

      ]
    },
    {
      "data" : {
        "tag" : "UI.Track.UrlD",
        "contents" : {
          "url" : "http:\/\/architecture.about.com\/cs\/historicperiods\/a\/timeline.htm"
        }
      },
      "title" : "Timeline - Architecture",
      "view" : {
        "tag" : "UI.ContentViews.Views.WebView"
      },
      "subtitle" : "Thoughtco",
      "expanded" : true,
      "children" : [

      ]
    },
    {
      "data" : {
        "tag" : "UI.Track.UrlD",
        "contents" : {
          "url" : "http:\/\/www.socialstudiesforkids.com\/"
        }
      },
      "title" : "www.socialstudiesforkids.com",
      "view" : {
        "tag" : "UI.ContentViews.Views.WebView"
      },
      "subtitle" : "www.socialstudiesforkids.com",
      "expanded" : true,
      "children" : [

      ]
    },
    {
      "data" : {
        "tag" : "UI.Track.UrlD",
        "contents" : {
          "url" : "http:\/\/smarthistory.khanacademy.org\/"
        }
      },
      "title" : "smarthistory.khanacademy.org",
      "view" : {
        "tag" : "UI.ContentViews.Views.WebView"
      },
      "subtitle" : "smarthistory.khanacademy.org",
      "expanded" : true,
      "children" : [

      ]
    },
    {
      "data" : {
        "tag" : "UI.Track.UrlD",
        "contents" : {
          "url" : "http:\/\/www.renaissanceconnection.org\/index2.cfm"
        }
      },
      "title" : "www.renaissanceconnection.org",
      "view" : {
        "tag" : "UI.ContentViews.Views.WebView"
      },
      "subtitle" : "www.renaissanceconnection.org",
      "expanded" : true,
      "children" : [

      ]
    },
    {
      "data" : {
        "tag" : "UI.Track.UrlD",
        "contents" : {
          "url" : "http:\/\/www.rocksinmyheadtoo.com\/TimeLine.htm"
        }
      },
      "title" : "Timeline - Geological History",
      "view" : {
        "tag" : "UI.ContentViews.Views.WebView"
      },
      "subtitle" : "www.rocksinmyheadtoo.com",
      "expanded" : true,
      "children" : [

      ]
    },
    {
      "data" : {
        "tag" : "UI.Track.UrlD",
        "contents" : {
          "url" : "http:\/\/www.historyworld.net\/timesearch\/default.asp?conid=1063"
        }
      },
      "title" : "Timeline - World History",
      "view" : {
        "tag" : "UI.ContentViews.Views.WebView"
      },
      "subtitle" : "www.historyworld.net",
      "expanded" : true,
      "children" : [

      ]
    },
    {
      "data" : {
        "tag" : "UI.Track.UrlD",
        "contents" : {
          "url" : "http:\/\/www.archives.gov\/exhibits\/charters\/bill_of_rights_zoom_1.html"
        }
      },
      "title" : "www.archives.gov",
      "view" : {
        "tag" : "UI.ContentViews.Views.WebView"
      },
      "subtitle" : "www.archives.gov",
      "expanded" : true,
      "children" : [

      ]
    }
  ]
}