{
  "title" : "Great Books",
  "subtitle" : "Archive ",
  "tracks" : [
    {
      "title" : "Great Books",
      "subtitle" : "Greek Authors",
      "track" : {
        "owner" : "oneeve8",
        "path" : "tracks\/greatbooksgreeks",
        "repo" : "kobble-data"
      }
    },
    {
      "title" : "Great Books",
      "subtitle" : "Roman Authors",
      "track" : {
        "owner" : "oneeve8",
        "path" : "tracks\/greatbooksromans",
        "repo" : "kobble-data"
      }
    },
    {
      "title" : "Great Books",
      "subtitle" : "Philosophers",
      "track" : {
        "owner" : "oneeve8",
        "path" : "tracks\/greatbooksphil",
        "repo" : "kobble-data"
      }
    },
    {
      "title" : "Great Books",
      "subtitle" : "Histories",
      "track" : {
        "owner" : "oneeve8",
        "path" : "tracks\/Greatbookshistories",
        "repo" : "kobble-data"
      }
    },
    {
      "title" : "Great Books",
      "subtitle" : "Science",
      "track" : {
        "owner" : "oneeve8",
        "path" : "tracks\/greatbooksscience",
        "repo" : "kobble-data"
      }
    },
    {
      "title" : "Great Books",
      "subtitle" : "Literature",
      "track" : {
        "owner" : "oneeve8",
        "path" : "tracks\/greatbookslit",
        "repo" : "kobble-data"
      }
    },
    {
      "title" : "Great Books ",
      "subtitle" : "American Authors",
      "track" : {
        "owner" : "oneeve8",
        "path" : "tracks\/greatbooksamerican",
        "repo" : "kobble-data"
      }
    },
    {
      "title" : "Great Books",
      "subtitle" : "Library",
      "track" : {
        "owner" : "oneeve8",
        "path" : "tracks\/greatbookslibrary",
        "repo" : "kobble-data"
      }
    },
    {
      "title" : "Great Books",
      "subtitle" : "Listed From #87",
      "track" : {
        "owner" : "oneeve8",
        "path" : "tracks\/greatbooks87",
        "repo" : "kobble-data"
      }
    }
  ]
}